{
  "results": [
    {
      "dappId": 29008
    },
    {
      "dappId": 29057
    },
    {
      "dappId": 29061
    },
    {
      "dappId": 29066
    },
    {
      "dappId": 29067
    },
    {
      "dappId": 29072
    },
    {
      "dappId": 29073
    },
    {
      "dappId": 29150
    },
    {
      "dappId": 29158
    },
    {
      "dappId": 29169
    },
    {
      "dappId": 29173
    },
    {
      "dappId": 29174
    },
    {
      "dappId": 29181
    },
    {
      "dappId": 29183
    },
    {
      "dappId": 29204
    },
    {
      "dappId": 29211
    },
    {
      "dappId": 29242
    },
    {
      "dappId": 0
    },
    {
      "dappId": 0
    }
  ]
}